dlp_mpi/__init__.py
dlp_mpi/collection.py
dlp_mpi/mpi.py
dlp_mpi/testing.py
dlp_mpi/util.py
dlp_mpi/callback/__init__.py
dlp_mpi/callback/module_map_unordered.py
dlp_mpi/split/__init__.py
dlp_mpi/split/managed.py
dlp_mpi/split/round_robin.py
dlp_mpi-0.0.4.dist-info/LICENSE
dlp_mpi-0.0.4.dist-info/METADATA
dlp_mpi-0.0.4.dist-info/WHEEL
dlp_mpi-0.0.4.dist-info/top_level.txt
dlp_mpi-0.0.4.dist-info/RECORD
