Metadata-Version: 2.1
Name: dlp-mpi
Version: 0.0.4
Summary: Data-level parallelism with mpi in python
Home-page: https://github.com/fgnt/dlp_mpi
Author: Christoph Boeddeker
Keywords: mpi
Classifier: Development Status :: 3 - Alpha
Classifier: Intended Audience :: Developers
Classifier: Topic :: Software Development :: Build Tools
Classifier: License :: OSI Approved :: MIT License
Classifier: Programming Language :: Python :: 3.6
Classifier: Programming Language :: Python :: 3.7
Requires-Python: >=3.6, <4
License-File: LICENSE
Requires-Dist: mpi4py
